winuserfolder/LICENSE
winuserfolder/README.MD
winuserfolder/__init__.py
winuserfolder/requirements.txt
winuserfolder/thirdparty.json
winuserfolder-0.10.dist-info/LICENSE.rst
winuserfolder-0.10.dist-info/METADATA
winuserfolder-0.10.dist-info/WHEEL
winuserfolder-0.10.dist-info/top_level.txt
winuserfolder-0.10.dist-info/RECORD
